pyhom/__init__.py
pyhom/pyhom_core.py
pyhom/built-in/dataset.zip
pyhom/full_field/Cell_Problem.py
pyhom/full_field/FF_Hom.py
pyhom/full_field/Linalg_FFT.py
pyhom/image_processing/Ellipses_Builder.py
pyhom/image_processing/Graph_Tools.py
pyhom/image_processing/Image.py
pyhom/image_processing/Tessellations.py
pyhom/mean_field/MF_Hom.py
pyhom/rsa/Build_RVE.py
pyhom-1.0.7.dist-info/METADATA
pyhom-1.0.7.dist-info/WHEEL
pyhom-1.0.7.dist-info/licenses/LICENSE
pyhom-1.0.7.dist-info/RECORD
