Metadata-Version: 2.4
Name: pyhom
Version: 1.0.7
Summary: PyHom: a Python library for homogenization
Project-URL: Homepage, https://github.com/olcruzgonzalez/pyhom
Project-URL: Issues, https://github.com/olcruzgonzalez/pyhom/issues
Author-email: "Oscar L. Cruz Gonzalez" <oscar.lcg93@gmail.com>
License-File: LICENSE
Classifier: License :: OSI Approved :: MIT License
Classifier: Operating System :: OS Independent
Classifier: Programming Language :: Python :: 3
Requires-Python: >=3.10
Requires-Dist: matplotlib==3.9.0
Requires-Dist: numpy==1.26.4
Requires-Dist: opencv-python==4.10.0.82
Requires-Dist: requests>=2.20
Requires-Dist: ruamel-yaml==0.18.6
Requires-Dist: scikit-image==0.23.2
Requires-Dist: shapely==2.0.4
Requires-Dist: sympy==1.12.1
Requires-Dist: tqdm==4.66.4
